flatten_codebase/__init__.py
flatten_codebase/main.py
flatten_codebase-1.3.dist-info/METADATA
flatten_codebase-1.3.dist-info/WHEEL
flatten_codebase-1.3.dist-info/entry_points.txt
flatten_codebase-1.3.dist-info/top_level.txt
flatten_codebase-1.3.dist-info/RECORD
