Metadata-Version: 2.1
Name: flatten-codebase
Version: 1.3
Summary: Flatten Codebase simplifies codebase preparation for Language Models by converting it into a single Markdown file, making it easier for the developer to provide the codebase to the LM
Home-page: https://github.com/VictorHenrique317/flatten-codebase
Author: Victor Henrique Silva Ribeiro
Author-email: victor.henrique5800@gmail.com
License: UNKNOWN
Platform: UNKNOWN
Classifier: Programming Language :: Python :: 3
Classifier: License :: OSI Approved :: MIT License
